franklins_scipy_safety_net/__init__.py
franklins_scipy_safety_net-0.0.1.dist-info/METADATA
franklins_scipy_safety_net-0.0.1.dist-info/WHEEL
franklins_scipy_safety_net-0.0.1.dist-info/licenses/LICENSE
franklins_scipy_safety_net-0.0.1.dist-info/RECORD
