Metadata-Version: 2.3
Name: franklins_scipy_safety_net
Version: 0.0.1
Summary: In a world full of SciPy puns, how to fit in
Project-URL: Homepage, https://github.com/fwkoch/franklins_scipy_safety_net
Project-URL: Issues, https://github.com/fwkoch/franklins_scipy_safety_net/issues
Author-email: Franklin Koch <franklinwkoch@gmail.com>
License-File: LICENSE
Classifier: License :: OSI Approved :: MIT License
Classifier: Operating System :: OS Independent
Classifier: Programming Language :: Python :: 3
Requires-Python: >=3.8
